{
  "report": "Advertiser earnings",
  "http": {
    "code": 200,
    "status": "OK"
  },
  "start": "2024-06-01",
  "end": "2024-06-07",
  "breakdown_period": "daily",
  "breakdown_level": "campaign",
  "structure": "flat",
  "data": {
    "2024-06": [
      {
        "advertiser": 101,
        "advertiser_name": "BetKing",
        "advertiserlogin": 201,
        "advertiserlogin_username": "affiliate_john",
        "campaignkey": "BK001",
        "campaignname": "Summer Promo",
        "date": "2024-06-01",
        "clicks": 85,
        "signups": 9,
        "active_players": 5,
        "deposits": 4,
        "FTD": 10,
        "CPA_count": 5,
        "unique_clicks": 51,
        "depositors": 8,
        "deposit_value": 524.02,
        "REV_income": 312.25,
        "bonus": 21.95,
        "netrevenue": 357.01,
        "turnover": 2387.52,
        "CPA_income": 68.08,
        "CPL_income": 46.11,
        "Extra_fee": "2.11"
      },
      {
        "advertiser": 101,
        "advertiser_name": "BetKing",
        "advertiserlogin": 202,
        "advertiserlogin_username": "partner_mary",
        "campaignkey": "BK001",
        "campaignname": "Summer Promo",
        "date": "2024-06-01",
        "clicks": 72,
        "signups": 28,
        "active_players": 17,
        "deposits": 2,
        "FTD": 2,
        "CPA_count": 4,
        "unique_clicks": 48,
        "depositors": 8,
        "deposit_value": 539.6,
        "REV_income": 150.15,
        "bonus": 15.26,
        "netrevenue": 785.55,
        "turnover": 2069.8,
        "CPA_income": 45.46,
        "CPL_income": 48.45,
        "Extra_fee": "1.52"
      },
      {
        "advertiser": 101,
        "advertiser_name": "BetKing",
        "advertiserlogin": 201,
        "advertiserlogin_username": "affiliate_john",
        "campaignkey": "SE002",
        "campaignname": "June Madness",
        "date": "2024-06-01",
        "clicks": 137,
        "signups": 18,
        "active_players": 20,
        "deposits": 10,
        "FTD": 7,
        "CPA_count": 10,
        "unique_clicks": 53,
        "depositors": 5,
        "deposit_value": 572.17,
        "REV_income": 396.32,
        "bonus": 21.16,
        "netrevenue": 510.38,
        "turnover": 1593.18,
        "CPA_income": 48.23,
        "CPL_income": 21.94,
        "Extra_fee": "4.04"
      },
      {
        "advertiser": 101,
        "advertiser_name": "BetKing",
        "advertiserlogin": 202,
        "advertiserlogin_username": "partner_mary",
        "campaignkey": "SE002",
        "campaignname": "June Madness",
        "date": "2024-06-01",
        "clicks": 126,
        "signups": 15,
        "active_players": 18,
        "deposits": 9,
        "FTD": 8,
        "CPA_count": 10,
        "unique_clicks": 63,
        "depositors": 10,
        "deposit_value": 146.65,
        "REV_income": 54.7,
        "bonus": 19.03,
        "netrevenue": 717.07,
        "turnover": 3293.26,
        "CPA_income": 69.46,
        "CPL_income": 27.01,
        "Extra_fee": "0.14"
      },
      {
        "advertiser": 102,
        "advertiser_name": "SlotEmpire",
        "advertiserlogin": 201,
        "advertiserlogin_username": "affiliate_john",
        "campaignkey": "BK001",
        "campaignname": "Summer Promo",
        "date": "2024-06-01",
        "clicks": 81,
        "signups": 9,
        "active_players": 13,
        "deposits": 9,
        "FTD": 6,
        "CPA_count": 8,
        "unique_clicks": 66,
        "depositors": 10,
        "deposit_value": 148.25,
        "REV_income": 226.76,
        "bonus": 14.74,
        "netrevenue": 505.73,
        "turnover": 1294.87,
        "CPA_income": 31.7,
        "CPL_income": 0.38,
        "Extra_fee": "0.89"
      },
      {
        "advertiser": 102,
        "advertiser_name": "SlotEmpire",
        "advertiserlogin": 202,
        "advertiserlogin_username": "partner_mary",
        "campaignkey": "BK001",
        "campaignname": "Summer Promo",
        "date": "2024-06-01",
        "clicks": 115,
        "signups": 21,
        "active_players": 17,
        "deposits": 10,
        "FTD": 4,
        "CPA_count": 8,
        "unique_clicks": 33,
        "depositors": 8,
        "deposit_value": 489.23,
        "REV_income": 250.07,
        "bonus": 7.62,
        "netrevenue": 594.51,
        "turnover": 2733.21,
        "CPA_income": 19.09,
        "CPL_income": 39.92,
        "Extra_fee": "0.82"
      },
      {
        "advertiser": 102,
        "advertiser_name": "SlotEmpire",
        "advertiserlogin": 201,
        "advertiserlogin_username": "affiliate_john",
        "campaignkey": "SE002",
        "campaignname": "June Madness",
        "date": "2024-06-01",
        "clicks": 157,
        "signups": 26,
        "active_players": 14,
        "deposits": 2,
        "FTD": 7,
        "CPA_count": 4,
        "unique_clicks": 75,
        "depositors": 7,
        "deposit_value": 731.64,
        "REV_income": 77.6,
        "bonus": 32.54,
        "netrevenue": 690.31,
        "turnover": 1184.34,
        "CPA_income": 67.69,
        "CPL_income": 0.6,
        "Extra_fee": "1.01"
      },
      {
        "advertiser": 102,
        "advertiser_name": "SlotEmpire",
        "advertiserlogin": 202,
        "advertiserlogin_username": "partner_mary",
        "campaignkey": "SE002",
        "campaignname": "June Madness",
        "date": "2024-06-01",
        "clicks": 77,
        "signups": 13,
        "active_players": 7,
        "deposits": 2,
        "FTD": 3,
        "CPA_count": 7,
        "unique_clicks": 82,
        "depositors": 6,
        "deposit_value": 262.6,
        "REV_income": 379.34,
        "bonus": 41.65,
        "netrevenue": 791.94,
        "turnover": 2752.21,
        "CPA_income": 88.04,
        "CPL_income": 10.26,
        "Extra_fee": "3.6"
      },
      {
        "advertiser": 101,
        "advertiser_name": "BetKing",
        "advertiserlogin": 201,
        "advertiserlogin_username": "affiliate_john",
        "campaignkey": "BK001",
        "campaignname": "Summer Promo",
        "date": "2024-06-02",
        "clicks": 131,
        "signups": 23,
        "active_players": 16,
        "deposits": 8,
        "FTD": 4,
        "CPA_count": 3,
        "unique_clicks": 74,
        "depositors": 8,
        "deposit_value": 168.25,
        "REV_income": 256.12,
        "bonus": 12.13,
        "netrevenue": 686.55,
        "turnover": 4008.1,
        "CPA_income": 56.08,
        "CPL_income": 23.15,
        "Extra_fee": "3.14"
      },
      {
        "advertiser": 101,
        "advertiser_name": "BetKing",
        "advertiserlogin": 202,
        "advertiserlogin_username": "partner_mary",
        "campaignkey": "BK001",
        "campaignname": "Summer Promo",
        "date": "2024-06-02",
        "clicks": 186,
        "signups": 27,
        "active_players": 6,
        "deposits": 9,
        "FTD": 10,
        "CPA_count": 8,
        "unique_clicks": 15,
        "depositors": 2,
        "deposit_value": 160.72,
        "REV_income": 325.39,
        "bonus": 7.74,
        "netrevenue": 237.57,
        "turnover": 4244.79,
        "CPA_income": 99.03,
        "CPL_income": 35.02,
        "Extra_fee": "4.62"
      },
      {
        "advertiser": 101,
        "advertiser_name": "BetKing",
        "advertiserlogin": 201,
        "advertiserlogin_username": "affiliate_john",
        "campaignkey": "SE002",
        "campaignname": "June Madness",
        "date": "2024-06-02",
        "clicks": 166,
        "signups": 14,
        "active_players": 19,
        "deposits": 2,
        "FTD": 7,
        "CPA_count": 0,
        "unique_clicks": 59,
        "depositors": 10,
        "deposit_value": 959.38,
        "REV_income": 141.57,
        "bonus": 13.64,
        "netrevenue": 486.58,
        "turnover": 4823.08,
        "CPA_income": 87.68,
        "CPL_income": 37.55,
        "Extra_fee": "4.44"
      },
      {
        "advertiser": 101,
        "advertiser_name": "BetKing",
        "advertiserlogin": 202,
        "advertiserlogin_username": "partner_mary",
        "campaignkey": "SE002",
        "campaignname": "June Madness",
        "date": "2024-06-02",
        "clicks": 79,
        "signups": 16,
        "active_players": 5,
        "deposits": 4,
        "FTD": 5,
        "CPA_count": 3,
        "unique_clicks": 87,
        "depositors": 0,
        "deposit_value": 843.35,
        "REV_income": 63.21,
        "bonus": 21.63,
        "netrevenue": 115.14,
        "turnover": 3504.31,
        "CPA_income": 99.41,
        "CPL_income": 35.25,
        "Extra_fee": "1.97"
      },
      {
        "advertiser": 102,
        "advertiser_name": "SlotEmpire",
        "advertiserlogin": 201,
        "advertiserlogin_username": "affiliate_john",
        "campaignkey": "BK001",
        "campaignname": "Summer Promo",
        "date": "2024-06-02",
        "clicks": 192,
        "signups": 26,
        "active_players": 2,
        "deposits": 3,
        "FTD": 1,
        "CPA_count": 3,
        "unique_clicks": 82,
        "depositors": 2,
        "deposit_value": 310.45,
        "REV_income": 51.99,
        "bonus": 22.42,
        "netrevenue": 494.21,
        "turnover": 2766.2,
        "CPA_income": 81.28,
        "CPL_income": 9.82,
        "Extra_fee": "0.46"
      },
      {
        "advertiser": 102,
        "advertiser_name": "SlotEmpire",
        "advertiserlogin": 202,
        "advertiserlogin_username": "partner_mary",
        "campaignkey": "BK001",
        "campaignname": "Summer Promo",
        "date": "2024-06-02",
        "clicks": 82,
        "signups": 5,
        "active_players": 8,
        "deposits": 5,
        "FTD": 1,
        "CPA_count": 2,
        "unique_clicks": 25,
        "depositors": 8,
        "deposit_value": 554.41,
        "REV_income": 72.6,
        "bonus": 43.79,
        "netrevenue": 380.14,
        "turnover": 2453.17,
        "CPA_income": 37.11,
        "CPL_income": 2.57,
        "Extra_fee": "1.79"
      },
      {
        "advertiser": 102,
        "advertiser_name": "SlotEmpire",
        "advertiserlogin": 201,
        "advertiserlogin_username": "affiliate_john",
        "campaignkey": "SE002",
        "campaignname": "June Madness",
        "date": "2024-06-02",
        "clicks": 140,
        "signups": 28,
        "active_players": 20,
        "deposits": 7,
        "FTD": 10,
        "CPA_count": 4,
        "unique_clicks": 83,
        "depositors": 5,
        "deposit_value": 511.72,
        "REV_income": 395.44,
        "bonus": 27.44,
        "netrevenue": 307.79,
        "turnover": 2887.51,
        "CPA_income": 10.35,
        "CPL_income": 21.66,
        "Extra_fee": "0.39"
      },
      {
        "advertiser": 102,
        "advertiser_name": "SlotEmpire",
        "advertiserlogin": 202,
        "advertiserlogin_username": "partner_mary",
        "campaignkey": "SE002",
        "campaignname": "June Madness",
        "date": "2024-06-02",
        "clicks": 108,
        "signups": 6,
        "active_players": 20,
        "deposits": 2,
        "FTD": 3,
        "CPA_count": 0,
        "unique_clicks": 30,
        "depositors": 1,
        "deposit_value": 849.14,
        "REV_income": 88.33,
        "bonus": 6.87,
        "netrevenue": 480.06,
        "turnover": 4670.44,
        "CPA_income": 79.15,
        "CPL_income": 39.68,
        "Extra_fee": "0.62"
      },
      {
        "advertiser": 101,
        "advertiser_name": "BetKing",
        "advertiserlogin": 201,
        "advertiserlogin_username": "affiliate_john",
        "campaignkey": "BK001",
        "campaignname": "Summer Promo",
        "date": "2024-06-03",
        "clicks": 191,
        "signups": 18,
        "active_players": 19,
        "deposits": 4,
        "FTD": 4,
        "CPA_count": 6,
        "unique_clicks": 81,
        "depositors": 3,
        "deposit_value": 927.36,
        "REV_income": 208.48,
        "bonus": 38.61,
        "netrevenue": 479.86,
        "turnover": 2337.97,
        "CPA_income": 50.38,
        "CPL_income": 28.2,
        "Extra_fee": "0.34"
      },
      {
        "advertiser": 101,
        "advertiser_name": "BetKing",
        "advertiserlogin": 202,
        "advertiserlogin_username": "partner_mary",
        "campaignkey": "BK001",
        "campaignname": "Summer Promo",
        "date": "2024-06-03",
        "clicks": 108,
        "signups": 15,
        "active_players": 3,
        "deposits": 4,
        "FTD": 8,
        "CPA_count": 8,
        "unique_clicks": 16,
        "depositors": 2,
        "deposit_value": 999.12,
        "REV_income": 392.12,
        "bonus": 5.69,
        "netrevenue": 150.01,
        "turnover": 3517.69,
        "CPA_income": 94.06,
        "CPL_income": 45.08,
        "Extra_fee": "4.84"
      },
      {
        "advertiser": 101,
        "advertiser_name": "BetKing",
        "advertiserlogin": 201,
        "advertiserlogin_username": "affiliate_john",
        "campaignkey": "SE002",
        "campaignname": "June Madness",
        "date": "2024-06-03",
        "clicks": 81,
        "signups": 21,
        "active_players": 14,
        "deposits": 2,
        "FTD": 7,
        "CPA_count": 6,
        "unique_clicks": 62,
        "depositors": 10,
        "deposit_value": 551.32,
        "REV_income": 211.46,
        "bonus": 23.82,
        "netrevenue": 709.75,
        "turnover": 4445.07,
        "CPA_income": 27.48,
        "CPL_income": 41.2,
        "Extra_fee": "1.78"
      },
      {
        "advertiser": 101,
        "advertiser_name": "BetKing",
        "advertiserlogin": 202,
        "advertiserlogin_username": "partner_mary",
        "campaignkey": "SE002",
        "campaignname": "June Madness",
        "date": "2024-06-03",
        "clicks": 181,
        "signups": 27,
        "active_players": 13,
        "deposits": 0,
        "FTD": 8,
        "CPA_count": 3,
        "unique_clicks": 18,
        "depositors": 3,
        "deposit_value": 322.03,
        "REV_income": 144.49,
        "bonus": 15.08,
        "netrevenue": 711.62,
        "turnover": 1702.99,
        "CPA_income": 26.11,
        "CPL_income": 3.4,
        "Extra_fee": "1.68"
      },
      {
        "advertiser": 102,
        "advertiser_name": "SlotEmpire",
        "advertiserlogin": 201,
        "advertiserlogin_username": "affiliate_john",
        "campaignkey": "BK001",
        "campaignname": "Summer Promo",
        "date": "2024-06-03",
        "clicks": 93,
        "signups": 9,
        "active_players": 7,
        "deposits": 7,
        "FTD": 6,
        "CPA_count": 1,
        "unique_clicks": 49,
        "depositors": 2,
        "deposit_value": 521.36,
        "REV_income": 197.16,
        "bonus": 8.25,
        "netrevenue": 678.4,
        "turnover": 2323.35,
        "CPA_income": 35.31,
        "CPL_income": 30.24,
        "Extra_fee": "0.06"
      },
      {
        "advertiser": 102,
        "advertiser_name": "SlotEmpire",
        "advertiserlogin": 202,
        "advertiserlogin_username": "partner_mary",
        "campaignkey": "BK001",
        "campaignname": "Summer Promo",
        "date": "2024-06-03",
        "clicks": 128,
        "signups": 5,
        "active_players": 20,
        "deposits": 9,
        "FTD": 5,
        "CPA_count": 9,
        "unique_clicks": 10,
        "depositors": 0,
        "deposit_value": 955.37,
        "REV_income": 197.47,
        "bonus": 7.56,
        "netrevenue": 172.4,
        "turnover": 2483.64,
        "CPA_income": 15.49,
        "CPL_income": 31.8,
        "Extra_fee": "2.22"
      },
      {
        "advertiser": 102,
        "advertiser_name": "SlotEmpire",
        "advertiserlogin": 201,
        "advertiserlogin_username": "affiliate_john",
        "campaignkey": "SE002",
        "campaignname": "June Madness",
        "date": "2024-06-03",
        "clicks": 92,
        "signups": 18,
        "active_players": 10,
        "deposits": 4,
        "FTD": 4,
        "CPA_count": 3,
        "unique_clicks": 86,
        "depositors": 10,
        "deposit_value": 421.77,
        "REV_income": 393.77,
        "bonus": 22.09,
        "netrevenue": 617.04,
        "turnover": 2263.28,
        "CPA_income": 13.14,
        "CPL_income": 29.49,
        "Extra_fee": "0.69"
      },
      {
        "advertiser": 102,
        "advertiser_name": "SlotEmpire",
        "advertiserlogin": 202,
        "advertiserlogin_username": "partner_mary",
        "campaignkey": "SE002",
        "campaignname": "June Madness",
        "date": "2024-06-03",
        "clicks": 133,
        "signups": 23,
        "active_players": 19,
        "deposits": 9,
        "FTD": 1,
        "CPA_count": 0,
        "unique_clicks": 94,
        "depositors": 8,
        "deposit_value": 564.21,
        "REV_income": 272.38,
        "bonus": 42.09,
        "netrevenue": 321.4,
        "turnover": 2152.12,
        "CPA_income": 17.67,
        "CPL_income": 29.43,
        "Extra_fee": "1.64"
      },
      {
        "advertiser": 101,
        "advertiser_name": "BetKing",
        "advertiserlogin": 201,
        "advertiserlogin_username": "affiliate_john",
        "campaignkey": "BK001",
        "campaignname": "Summer Promo",
        "date": "2024-06-04",
        "clicks": 138,
        "signups": 17,
        "active_players": 9,
        "deposits": 2,
        "FTD": 7,
        "CPA_count": 6,
        "unique_clicks": 43,
        "depositors": 6,
        "deposit_value": 962.28,
        "REV_income": 293.85,
        "bonus": 8.84,
        "netrevenue": 283.51,
        "turnover": 1096.55,
        "CPA_income": 93.04,
        "CPL_income": 24.06,
        "Extra_fee": "0.89"
      },
      {
        "advertiser": 101,
        "advertiser_name": "BetKing",
        "advertiserlogin": 202,
        "advertiserlogin_username": "partner_mary",
        "campaignkey": "BK001",
        "campaignname": "Summer Promo",
        "date": "2024-06-04",
        "clicks": 177,
        "signups": 7,
        "active_players": 8,
        "deposits": 6,
        "FTD": 0,
        "CPA_count": 10,
        "unique_clicks": 44,
        "depositors": 10,
        "deposit_value": 329.75,
        "REV_income": 186.24,
        "bonus": 0.28,
        "netrevenue": 337.16,
        "turnover": 4992.53,
        "CPA_income": 50.43,
        "CPL_income": 25.53,
        "Extra_fee": "4.22"
      },
      {
        "advertiser": 101,
        "advertiser_name": "BetKing",
        "advertiserlogin": 201,
        "advertiserlogin_username": "affiliate_john",
        "campaignkey": "SE002",
        "campaignname": "June Madness",
        "date": "2024-06-04",
        "clicks": 162,
        "signups": 25,
        "active_players": 19,
        "deposits": 8,
        "FTD": 1,
        "CPA_count": 2,
        "unique_clicks": 95,
        "depositors": 7,
        "deposit_value": 762.26,
        "REV_income": 95.13,
        "bonus": 49.34,
        "netrevenue": 429.97,
        "turnover": 1403.71,
        "CPA_income": 68.84,
        "CPL_income": 1.71,
        "Extra_fee": "0.92"
      },
      {
        "advertiser": 101,
        "advertiser_name": "BetKing",
        "advertiserlogin": 202,
        "advertiserlogin_username": "partner_mary",
        "campaignkey": "SE002",
        "campaignname": "June Madness",
        "date": "2024-06-04",
        "clicks": 180,
        "signups": 25,
        "active_players": 11,
        "deposits": 6,
        "FTD": 5,
        "CPA_count": 9,
        "unique_clicks": 79,
        "depositors": 8,
        "deposit_value": 792.15,
        "REV_income": 208.45,
        "bonus": 30.47,
        "netrevenue": 686.44,
        "turnover": 2263.34,
        "CPA_income": 82.67,
        "CPL_income": 46.33,
        "Extra_fee": "1.97"
      },
      {
        "advertiser": 102,
        "advertiser_name": "SlotEmpire",
        "advertiserlogin": 201,
        "advertiserlogin_username": "affiliate_john",
        "campaignkey": "BK001",
        "campaignname": "Summer Promo",
        "date": "2024-06-04",
        "clicks": 72,
        "signups": 18,
        "active_players": 16,
        "deposits": 5,
        "FTD": 8,
        "CPA_count": 4,
        "unique_clicks": 27,
        "depositors": 8,
        "deposit_value": 369.31,
        "REV_income": 310.02,
        "bonus": 15.4,
        "netrevenue": 140.66,
        "turnover": 2393.38,
        "CPA_income": 14.34,
        "CPL_income": 16.51,
        "Extra_fee": "0.02"
      },
      {
        "advertiser": 102,
        "advertiser_name": "SlotEmpire",
        "advertiserlogin": 202,
        "advertiserlogin_username": "partner_mary",
        "campaignkey": "BK001",
        "campaignname": "Summer Promo",
        "date": "2024-06-04",
        "clicks": 101,
        "signups": 14,
        "active_players": 14,
        "deposits": 8,
        "FTD": 2,
        "CPA_count": 1,
        "unique_clicks": 23,
        "depositors": 5,
        "deposit_value": 716.02,
        "REV_income": 70.01,
        "bonus": 48.59,
        "netrevenue": 659.51,
        "turnover": 1651.16,
        "CPA_income": 53.02,
        "CPL_income": 31.74,
        "Extra_fee": "4.21"
      },
      {
        "advertiser": 102,
        "advertiser_name": "SlotEmpire",
        "advertiserlogin": 201,
        "advertiserlogin_username": "affiliate_john",
        "campaignkey": "SE002",
        "campaignname": "June Madness",
        "date": "2024-06-04",
        "clicks": 106,
        "signups": 6,
        "active_players": 15,
        "deposits": 8,
        "FTD": 1,
        "CPA_count": 2,
        "unique_clicks": 36,
        "depositors": 2,
        "deposit_value": 145.95,
        "REV_income": 245.72,
        "bonus": 48.24,
        "netrevenue": 735.21,
        "turnover": 1337.64,
        "CPA_income": 19.12,
        "CPL_income": 27.36,
        "Extra_fee": "1.32"
      },
      {
        "advertiser": 102,
        "advertiser_name": "SlotEmpire",
        "advertiserlogin": 202,
        "advertiserlogin_username": "partner_mary",
        "campaignkey": "SE002",
        "campaignname": "June Madness",
        "date": "2024-06-04",
        "clicks": 75,
        "signups": 9,
        "active_players": 10,
        "deposits": 10,
        "FTD": 9,
        "CPA_count": 8,
        "unique_clicks": 66,
        "depositors": 10,
        "deposit_value": 997.54,
        "REV_income": 306.62,
        "bonus": 40.29,
        "netrevenue": 230.75,
        "turnover": 1403.71,
        "CPA_income": 91.66,
        "CPL_income": 19.49,
        "Extra_fee": "2.07"
      },
      {
        "advertiser": 101,
        "advertiser_name": "BetKing",
        "advertiserlogin": 201,
        "advertiserlogin_username": "affiliate_john",
        "campaignkey": "BK001",
        "campaignname": "Summer Promo",
        "date": "2024-06-05",
        "clicks": 159,
        "signups": 13,
        "active_players": 13,
        "deposits": 3,
        "FTD": 2,
        "CPA_count": 8,
        "unique_clicks": 69,
        "depositors": 8,
        "deposit_value": 164.8,
        "REV_income": 90.74,
        "bonus": 11.68,
        "netrevenue": 384.17,
        "turnover": 4892.32,
        "CPA_income": 43.85,
        "CPL_income": 48.07,
        "Extra_fee": "0.98"
      },
      {
        "advertiser": 101,
        "advertiser_name": "BetKing",
        "advertiserlogin": 202,
        "advertiserlogin_username": "partner_mary",
        "campaignkey": "BK001",
        "campaignname": "Summer Promo",
        "date": "2024-06-05",
        "clicks": 52,
        "signups": 19,
        "active_players": 6,
        "deposits": 8,
        "FTD": 2,
        "CPA_count": 6,
        "unique_clicks": 68,
        "depositors": 9,
        "deposit_value": 217.27,
        "REV_income": 332.55,
        "bonus": 48.96,
        "netrevenue": 680.29,
        "turnover": 1255.91,
        "CPA_income": 87.98,
        "CPL_income": 34.04,
        "Extra_fee": "0.63"
      },
      {
        "advertiser": 101,
        "advertiser_name": "BetKing",
        "advertiserlogin": 201,
        "advertiserlogin_username": "affiliate_john",
        "campaignkey": "SE002",
        "campaignname": "June Madness",
        "date": "2024-06-05",
        "clicks": 181,
        "signups": 14,
        "active_players": 20,
        "deposits": 2,
        "FTD": 8,
        "CPA_count": 6,
        "unique_clicks": 81,
        "depositors": 3,
        "deposit_value": 657.9,
        "REV_income": 296.27,
        "bonus": 31.04,
        "netrevenue": 276.15,
        "turnover": 3728.28,
        "CPA_income": 12.63,
        "CPL_income": 20.65,
        "Extra_fee": "0.63"
      },
      {
        "advertiser": 101,
        "advertiser_name": "BetKing",
        "advertiserlogin": 202,
        "advertiserlogin_username": "partner_mary",
        "campaignkey": "SE002",
        "campaignname": "June Madness",
        "date": "2024-06-05",
        "clicks": 71,
        "signups": 8,
        "active_players": 7,
        "deposits": 10,
        "FTD": 3,
        "CPA_count": 2,
        "unique_clicks": 10,
        "depositors": 9,
        "deposit_value": 792.81,
        "REV_income": 138.25,
        "bonus": 6.58,
        "netrevenue": 757.21,
        "turnover": 4982.24,
        "CPA_income": 97.42,
        "CPL_income": 47.16,
        "Extra_fee": "1.76"
      },
      {
        "advertiser": 102,
        "advertiser_name": "SlotEmpire",
        "advertiserlogin": 201,
        "advertiserlogin_username": "affiliate_john",
        "campaignkey": "BK001",
        "campaignname": "Summer Promo",
        "date": "2024-06-05",
        "clicks": 185,
        "signups": 9,
        "active_players": 1,
        "deposits": 6,
        "FTD": 0,
        "CPA_count": 9,
        "unique_clicks": 59,
        "depositors": 10,
        "deposit_value": 528.59,
        "REV_income": 94.64,
        "bonus": 5.65,
        "netrevenue": 315.15,
        "turnover": 4319.37,
        "CPA_income": 61.0,
        "CPL_income": 44.02,
        "Extra_fee": "4.76"
      },
      {
        "advertiser": 102,
        "advertiser_name": "SlotEmpire",
        "advertiserlogin": 202,
        "advertiserlogin_username": "partner_mary",
        "campaignkey": "BK001",
        "campaignname": "Summer Promo",
        "date": "2024-06-05",
        "clicks": 122,
        "signups": 14,
        "active_players": 6,
        "deposits": 3,
        "FTD": 8,
        "CPA_count": 10,
        "unique_clicks": 96,
        "depositors": 5,
        "deposit_value": 518.63,
        "REV_income": 182.99,
        "bonus": 40.74,
        "netrevenue": 514.51,
        "turnover": 2496.5,
        "CPA_income": 31.17,
        "CPL_income": 30.82,
        "Extra_fee": "2.4"
      },
      {
        "advertiser": 102,
        "advertiser_name": "SlotEmpire",
        "advertiserlogin": 201,
        "advertiserlogin_username": "affiliate_john",
        "campaignkey": "SE002",
        "campaignname": "June Madness",
        "date": "2024-06-05",
        "clicks": 84,
        "signups": 15,
        "active_players": 17,
        "deposits": 7,
        "FTD": 7,
        "CPA_count": 5,
        "unique_clicks": 23,
        "depositors": 2,
        "deposit_value": 666.16,
        "REV_income": 167.15,
        "bonus": 6.61,
        "netrevenue": 556.69,
        "turnover": 3970.29,
        "CPA_income": 17.31,
        "CPL_income": 19.55,
        "Extra_fee": "1.0"
      },
      {
        "advertiser": 102,
        "advertiser_name": "SlotEmpire",
        "advertiserlogin": 202,
        "advertiserlogin_username": "partner_mary",
        "campaignkey": "SE002",
        "campaignname": "June Madness",
        "date": "2024-06-05",
        "clicks": 163,
        "signups": 7,
        "active_players": 1,
        "deposits": 3,
        "FTD": 9,
        "CPA_count": 3,
        "unique_clicks": 35,
        "depositors": 6,
        "deposit_value": 419.4,
        "REV_income": 290.82,
        "bonus": 0.02,
        "netrevenue": 316.06,
        "turnover": 1298.86,
        "CPA_income": 16.77,
        "CPL_income": 27.51,
        "Extra_fee": "1.49"
      },
      {
        "advertiser": 101,
        "advertiser_name": "BetKing",
        "advertiserlogin": 201,
        "advertiserlogin_username": "affiliate_john",
        "campaignkey": "BK001",
        "campaignname": "Summer Promo",
        "date": "2024-06-06",
        "clicks": 156,
        "signups": 13,
        "active_players": 16,
        "deposits": 2,
        "FTD": 7,
        "CPA_count": 0,
        "unique_clicks": 35,
        "depositors": 6,
        "deposit_value": 784.22,
        "REV_income": 295.67,
        "bonus": 9.6,
        "netrevenue": 792.86,
        "turnover": 3301.13,
        "CPA_income": 75.16,
        "CPL_income": 46.12,
        "Extra_fee": "2.01"
      },
      {
        "advertiser": 101,
        "advertiser_name": "BetKing",
        "advertiserlogin": 202,
        "advertiserlogin_username": "partner_mary",
        "campaignkey": "BK001",
        "campaignname": "Summer Promo",
        "date": "2024-06-06",
        "clicks": 111,
        "signups": 29,
        "active_players": 14,
        "deposits": 10,
        "FTD": 10,
        "CPA_count": 2,
        "unique_clicks": 77,
        "depositors": 9,
        "deposit_value": 903.54,
        "REV_income": 81.02,
        "bonus": 31.32,
        "netrevenue": 336.19,
        "turnover": 3923.99,
        "CPA_income": 30.89,
        "CPL_income": 12.66,
        "Extra_fee": "1.91"
      },
      {
        "advertiser": 101,
        "advertiser_name": "BetKing",
        "advertiserlogin": 201,
        "advertiserlogin_username": "affiliate_john",
        "campaignkey": "SE002",
        "campaignname": "June Madness",
        "date": "2024-06-06",
        "clicks": 94,
        "signups": 18,
        "active_players": 5,
        "deposits": 5,
        "FTD": 3,
        "CPA_count": 3,
        "unique_clicks": 45,
        "depositors": 7,
        "deposit_value": 530.36,
        "REV_income": 376.16,
        "bonus": 25.35,
        "netrevenue": 244.36,
        "turnover": 2340.93,
        "CPA_income": 58.84,
        "CPL_income": 10.62,
        "Extra_fee": "2.17"
      },
      {
        "advertiser": 101,
        "advertiser_name": "BetKing",
        "advertiserlogin": 202,
        "advertiserlogin_username": "partner_mary",
        "campaignkey": "SE002",
        "campaignname": "June Madness",
        "date": "2024-06-06",
        "clicks": 62,
        "signups": 29,
        "active_players": 1,
        "deposits": 7,
        "FTD": 8,
        "CPA_count": 4,
        "unique_clicks": 96,
        "depositors": 0,
        "deposit_value": 722.56,
        "REV_income": 126.25,
        "bonus": 19.62,
        "netrevenue": 555.56,
        "turnover": 2552.18,
        "CPA_income": 14.44,
        "CPL_income": 7.16,
        "Extra_fee": "2.98"
      },
      {
        "advertiser": 102,
        "advertiser_name": "SlotEmpire",
        "advertiserlogin": 201,
        "advertiserlogin_username": "affiliate_john",
        "campaignkey": "BK001",
        "campaignname": "Summer Promo",
        "date": "2024-06-06",
        "clicks": 70,
        "signups": 13,
        "active_players": 9,
        "deposits": 4,
        "FTD": 5,
        "CPA_count": 7,
        "unique_clicks": 81,
        "depositors": 2,
        "deposit_value": 979.87,
        "REV_income": 232.24,
        "bonus": 29.51,
        "netrevenue": 787.89,
        "turnover": 4646.97,
        "CPA_income": 83.55,
        "CPL_income": 33.44,
        "Extra_fee": "0.5"
      },
      {
        "advertiser": 102,
        "advertiser_name": "SlotEmpire",
        "advertiserlogin": 202,
        "advertiserlogin_username": "partner_mary",
        "campaignkey": "BK001",
        "campaignname": "Summer Promo",
        "date": "2024-06-06",
        "clicks": 152,
        "signups": 23,
        "active_players": 4,
        "deposits": 2,
        "FTD": 4,
        "CPA_count": 2,
        "unique_clicks": 81,
        "depositors": 3,
        "deposit_value": 656.66,
        "REV_income": 88.74,
        "bonus": 21.19,
        "netrevenue": 776.93,
        "turnover": 2318.9,
        "CPA_income": 35.87,
        "CPL_income": 44.16,
        "Extra_fee": "2.34"
      },
      {
        "advertiser": 102,
        "advertiser_name": "SlotEmpire",
        "advertiserlogin": 201,
        "advertiserlogin_username": "affiliate_john",
        "campaignkey": "SE002",
        "campaignname": "June Madness",
        "date": "2024-06-06",
        "clicks": 107,
        "signups": 18,
        "active_players": 15,
        "deposits": 5,
        "FTD": 6,
        "CPA_count": 8,
        "unique_clicks": 56,
        "depositors": 6,
        "deposit_value": 501.25,
        "REV_income": 288.48,
        "bonus": 40.39,
        "netrevenue": 473.3,
        "turnover": 2133.04,
        "CPA_income": 66.12,
        "CPL_income": 5.41,
        "Extra_fee": "0.27"
      },
      {
        "advertiser": 102,
        "advertiser_name": "SlotEmpire",
        "advertiserlogin": 202,
        "advertiserlogin_username": "partner_mary",
        "campaignkey": "SE002",
        "campaignname": "June Madness",
        "date": "2024-06-06",
        "clicks": 96,
        "signups": 27,
        "active_players": 2,
        "deposits": 2,
        "FTD": 10,
        "CPA_count": 9,
        "unique_clicks": 54,
        "depositors": 5,
        "deposit_value": 764.5,
        "REV_income": 121.97,
        "bonus": 10.69,
        "netrevenue": 540.85,
        "turnover": 4567.12,
        "CPA_income": 78.39,
        "CPL_income": 42.81,
        "Extra_fee": "2.71"
      },
      {
        "advertiser": 101,
        "advertiser_name": "BetKing",
        "advertiserlogin": 201,
        "advertiserlogin_username": "affiliate_john",
        "campaignkey": "BK001",
        "campaignname": "Summer Promo",
        "date": "2024-06-07",
        "clicks": 77,
        "signups": 23,
        "active_players": 6,
        "deposits": 5,
        "FTD": 2,
        "CPA_count": 6,
        "unique_clicks": 69,
        "depositors": 7,
        "deposit_value": 618.99,
        "REV_income": 384.92,
        "bonus": 44.38,
        "netrevenue": 736.25,
        "turnover": 1576.75,
        "CPA_income": 93.49,
        "CPL_income": 19.8,
        "Extra_fee": "4.31"
      },
      {
        "advertiser": 101,
        "advertiser_name": "BetKing",
        "advertiserlogin": 202,
        "advertiserlogin_username": "partner_mary",
        "campaignkey": "BK001",
        "campaignname": "Summer Promo",
        "date": "2024-06-07",
        "clicks": 78,
        "signups": 6,
        "active_players": 15,
        "deposits": 9,
        "FTD": 6,
        "CPA_count": 5,
        "unique_clicks": 42,
        "depositors": 3,
        "deposit_value": 869.31,
        "REV_income": 216.74,
        "bonus": 25.85,
        "netrevenue": 244.13,
        "turnover": 3036.0,
        "CPA_income": 90.59,
        "CPL_income": 21.88,
        "Extra_fee": "0.56"
      },
      {
        "advertiser": 101,
        "advertiser_name": "BetKing",
        "advertiserlogin": 201,
        "advertiserlogin_username": "affiliate_john",
        "campaignkey": "SE002",
        "campaignname": "June Madness",
        "date": "2024-06-07",
        "clicks": 170,
        "signups": 14,
        "active_players": 6,
        "deposits": 6,
        "FTD": 7,
        "CPA_count": 10,
        "unique_clicks": 88,
        "depositors": 6,
        "deposit_value": 784.07,
        "REV_income": 367.92,
        "bonus": 38.81,
        "netrevenue": 164.4,
        "turnover": 1349.77,
        "CPA_income": 20.66,
        "CPL_income": 19.96,
        "Extra_fee": "1.6"
      },
      {
        "advertiser": 101,
        "advertiser_name": "BetKing",
        "advertiserlogin": 202,
        "advertiserlogin_username": "partner_mary",
        "campaignkey": "SE002",
        "campaignname": "June Madness",
        "date": "2024-06-07",
        "clicks": 115,
        "signups": 9,
        "active_players": 7,
        "deposits": 4,
        "FTD": 4,
        "CPA_count": 6,
        "unique_clicks": 55,
        "depositors": 6,
        "deposit_value": 233.1,
        "REV_income": 350.91,
        "bonus": 32.03,
        "netrevenue": 357.79,
        "turnover": 4570.59,
        "CPA_income": 59.71,
        "CPL_income": 31.49,
        "Extra_fee": "0.69"
      },
      {
        "advertiser": 102,
        "advertiser_name": "SlotEmpire",
        "advertiserlogin": 201,
        "advertiserlogin_username": "affiliate_john",
        "campaignkey": "BK001",
        "campaignname": "Summer Promo",
        "date": "2024-06-07",
        "clicks": 162,
        "signups": 12,
        "active_players": 2,
        "deposits": 7,
        "FTD": 4,
        "CPA_count": 7,
        "unique_clicks": 90,
        "depositors": 8,
        "deposit_value": 136.06,
        "REV_income": 238.15,
        "bonus": 25.98,
        "netrevenue": 299.62,
        "turnover": 4172.15,
        "CPA_income": 43.04,
        "CPL_income": 41.18,
        "Extra_fee": "2.83"
      },
      {
        "advertiser": 102,
        "advertiser_name": "SlotEmpire",
        "advertiserlogin": 202,
        "advertiserlogin_username": "partner_mary",
        "campaignkey": "BK001",
        "campaignname": "Summer Promo",
        "date": "2024-06-07",
        "clicks": 65,
        "signups": 18,
        "active_players": 3,
        "deposits": 8,
        "FTD": 6,
        "CPA_count": 1,
        "unique_clicks": 72,
        "depositors": 6,
        "deposit_value": 376.18,
        "REV_income": 246.32,
        "bonus": 33.62,
        "netrevenue": 331.07,
        "turnover": 2302.98,
        "CPA_income": 52.91,
        "CPL_income": 28.7,
        "Extra_fee": "1.93"
      },
      {
        "advertiser": 102,
        "advertiser_name": "SlotEmpire",
        "advertiserlogin": 201,
        "advertiserlogin_username": "affiliate_john",
        "campaignkey": "SE002",
        "campaignname": "June Madness",
        "date": "2024-06-07",
        "clicks": 128,
        "signups": 17,
        "active_players": 1,
        "deposits": 2,
        "FTD": 5,
        "CPA_count": 1,
        "unique_clicks": 49,
        "depositors": 2,
        "deposit_value": 283.26,
        "REV_income": 107.32,
        "bonus": 17.28,
        "netrevenue": 771.31,
        "turnover": 1326.14,
        "CPA_income": 32.36,
        "CPL_income": 47.36,
        "Extra_fee": "4.46"
      },
      {
        "advertiser": 102,
        "advertiser_name": "SlotEmpire",
        "advertiserlogin": 202,
        "advertiserlogin_username": "partner_mary",
        "campaignkey": "SE002",
        "campaignname": "June Madness",
        "date": "2024-06-07",
        "clicks": 74,
        "signups": 25,
        "active_players": 3,
        "deposits": 7,
        "FTD": 8,
        "CPA_count": 6,
        "unique_clicks": 86,
        "depositors": 6,
        "deposit_value": 354.43,
        "REV_income": 298.79,
        "bonus": 9.75,
        "netrevenue": 277.78,
        "turnover": 1155.62,
        "CPA_income": 85.39,
        "CPL_income": 21.54,
        "Extra_fee": "1.56"
      }
    ]
  }
}